wgfapy/__init__.py
wgfapy/__main__.py
wgfapy/app.py
wgfapy/assembler/__init__.py
wgfapy/assembler/header.py
wgfapy/assembler/ops.py
wgfapy/fragment.py
wgfapy/io/__init__.py
wgfapy/io/app.py
wgfapy/io/create.py
wgfapy/io/iter.py
wgfapy/iter.py
wgfapy/lines/__init__.py
wgfapy/lines/flag.py
wgfapy/lines/header.py
wgfapy/lines/link.py
wgfapy/lines/path.py
wgfapy/lines/properties.py
wgfapy/lines/segment.py
wgfapy/link.py
wgfapy/ops/__init__.py
wgfapy/ops/app.py
wgfapy/ops/fix/__init__.py
wgfapy/ops/fix/app.py
wgfapy/ops/fix/ops.py
wgfapy/ops/std/__init__.py
wgfapy/ops/std/app.py
wgfapy/ops/std/lines.py
wgfapy/ops/std/ops.py
wgfapy/ops/sub/__init__.py
wgfapy/ops/sub/app.py
wgfapy/ops/sub/ops.py
wgfapy/py.typed
wgfapy/root_logging.py
wgfapy/utils/__init__.py
wgfapy/utils/io.py
wgfapy/views/__init__.py
wgfapy/views/app.py
gfapy_wrap-0.0.4.dist-info/WHEEL
gfapy_wrap-0.0.4.dist-info/entry_points.txt
gfapy_wrap-0.0.4.dist-info/METADATA
gfapy_wrap-0.0.4.dist-info/RECORD
