Metadata-Version: 2.3
Name: gfapy-wrap
Version: 0.0.4
Summary: Python wrapper for gfapy.
Author: vepain
Author-email: vepain <victorepain@disroot.org>
License: # GNU GENERAL PUBLIC LICENSE
Requires-Dist: typer>=0.20,<1.0
Requires-Dist: gfapy>=1.2,<2.0
Requires-Dist: networkx>=3.5,<4.0
Requires-Dist: biopython>=1.85,<2.0
Requires-Dist: returns>=0.26,<1.0
Requires-Python: >=3.13
Project-URL: Changelog, https://gitlab.com/vepain/gfapy_wrap-py/-/blob/main/CHANGELOG.md
Project-URL: Repository, https://gitlab.com/vepain/gfapy_wrap-py
